README.rst
pyproject.toml
setup.py
mkdocs_docslab/__init__.py
mkdocs_docslab/_version.py
mkdocs_docslab.egg-info/PKG-INFO
mkdocs_docslab.egg-info/SOURCES.txt
mkdocs_docslab.egg-info/dependency_links.txt
mkdocs_docslab.egg-info/entry_points.txt
mkdocs_docslab.egg-info/requires.txt
mkdocs_docslab.egg-info/top_level.txt